holtz_tools-0.4.3.dist-info/licenses/LICENSE
holtztools/__init__.py
holtztools/fit.py
holtztools/html.py
holtztools/match.py
holtztools/plots.py
holtztools/reminder.py
holtztools/struct.py
holtz_tools-0.4.3.dist-info/METADATA
holtz_tools-0.4.3.dist-info/WHEEL
holtz_tools-0.4.3.dist-info/top_level.txt
holtz_tools-0.4.3.dist-info/RECORD
