Metadata-Version: 2.4
Name: holtz-tools
Version: 0.4.3
Summary: Python utility tools
Author-email: Jon Holtzman <holtzmanjon@gmail.com>
Project-URL: Homepage, https://github.com/holtzmanjon/tools
Classifier: Development Status :: 1 - Planning
Classifier: Intended Audience :: Science/Research
Classifier: License :: OSI Approved :: BSD License
Classifier: Operating System :: OS Independent
Classifier: Programming Language :: Python :: 3
Requires-Python: >=3.9
License-File: LICENSE
Requires-Dist: matplotlib
Requires-Dist: numpy
Requires-Dist: scipy
Requires-Dist: bokeh
Requires-Dist: astropy
Dynamic: license-file
